Metadata-Version: 2.1
Name: cs1440-arena
Version: 0.3.5
Summary: A Go game arena for CS410 bot competitions
Home-page: https://github.com/brown-cs-410/cs410-arena
Author: John Wu
Author-email: john_wu@brown.edu
License: UNKNOWN
Platform: UNKNOWN
Classifier: Programming Language :: Python :: 3
Classifier: License :: OSI Approved :: MIT License
Classifier: Operating System :: OS Independent
Requires-Python: >=3.8
Requires-Dist: numpy >=1.24.3
Requires-Dist: flask >=2.0.0
Requires-Dist: requests >=2.25.1
Requires-Dist: open-spiel >=1.4.0
